{
    "@class": "Animation",
    "id": {
        "uuid": "50545ACE-1C2D-464E-9B60-6137B4463149"
    },
    "tracks": [
        {
            "@class": "Vector3BehaviorTrack",
            "clips": [
                {
                    "@class": "Vector3BehaviorClip",
                    "beginTime": 0,
                    "duration": 433,
                    "script": "Vector3ValueBehaviorClipScript",
                    "behavior": {
                        "@class": "Vector3PlainBehavior",
                        "times": [
                            0,
                            33,
                            66,
                            99,
                            133,
                            166,
                            199,
                            233,
                            266,
                            299,
                            333,
                            366,
                            399,
                            433
                        ],
                        "values": [
                            -1.3154931366443634e-8,
                            0.1292409598827362,
                            2.827655407600105e-7,
                            -1.3154931366443634e-8,
                            0.1292409598827362,
                            2.827655407600105e-7,
                            -1.3154931366443634e-8,
                            0.1292409598827362,
                            2.827655407600105e-7,
                            -1.3154931366443634e-8,
                            0.1292409598827362,
                            2.827655407600105e-7,
                            -1.3154931366443634e-8,
                            0.1292409598827362,
                            2.827655407600105e-7,
                            -1.3154931366443634e-8,
                            0.1292409598827362,
                            2.827655407600105e-7,
                            -1.3154931366443634e-8,
                            0.1292409598827362,
                            2.827655407600105e-7,
                            -1.3154931366443634e-8,
                            0.1292409598827362,
                            2.827655407600105e-7,
                            -1.3154931366443634e-8,
                            0.1292409598827362,
                            2.827655407600105e-7,
                            -1.3154931366443634e-8,
                            0.1292409598827362,
                            2.827655407600105e-7,
                            -1.3154931366443634e-8,
                            0.1292409598827362,
                            2.827655407600105e-7,
                            -1.3154931366443634e-8,
                            0.1292409598827362,
                            2.827655407600105e-7,
                            -1.3154931366443634e-8,
                            0.1292409598827362,
                            2.827655407600105e-7,
                            -1.3154931366443634e-8,
                            0.1292409598827362,
                            2.827655407600105e-7
                        ]
                    }
                }
            ],
            "script": "Vector3BehaviorTrackScript",
            "accessor": "PositionBlendAccessor"
        },
        {
            "@class": "QuaternionBehaviorTrack",
            "clips": [
                {
                    "@class": "QuaternionBehaviorClip",
                    "beginTime": 0,
                    "duration": 433,
                    "script": "QuaternionValueBehaviorClipScript",
                    "behavior": {
                        "@class": "QuaternionPlainBehavior",
                        "times": [
                            0,
                            33,
                            66,
                            99,
                            133,
                            166,
                            199,
                            233,
                            266,
                            299,
                            333,
                            366,
                            399,
                            433
                        ],
                        "values": [
                            -0.10993436723947525,
                            -0.26339590549468996,
                            0.2750284671783447,
                            0.9180939197540283,
                            -0.0758451446890831,
                            -0.26465609669685366,
                            0.28673622012138369,
                            0.9175984859466553,
                            -0.00044395538861863315,
                            -0.2716553211212158,
                            0.30424001812934878,
                            0.9130395650863648,
                            0.05748425051569939,
                            -0.28799524903297427,
                            0.2979391813278198,
                            0.9082877039909363,
                            0.058618947863578799,
                            -0.32027584314346316,
                            0.31845903396606448,
                            0.890264630317688,
                            0.07668183743953705,
                            -0.34302809834480288,
                            0.38371700048446658,
                            0.8539396524429321,
                            0.16460540890693665,
                            -0.30853211879730227,
                            0.3795914351940155,
                            0.8565181493759155,
                            0.3005259037017822,
                            -0.19870346784591676,
                            0.2248743623495102,
                            0.9053356647491455,
                            0.3575400412082672,
                            -0.10188311338424683,
                            0.14506299793720246,
                            0.9169196486473084,
                            0.30839428305625918,
                            -0.06643817573785782,
                            0.2424570769071579,
                            0.9174385666847229,
                            0.1332220733165741,
                            -0.17075683176517487,
                            0.4673212766647339,
                            0.8571492433547974,
                            -0.054086387157440189,
                            -0.32942643761634829,
                            0.37337130308151247,
                            0.865532636642456,
                            -0.0042901658453047279,
                            -0.3772261142730713,
                            0.17599676549434663,
                            0.9092344045639038,
                            -0.06298039108514786,
                            -0.4320351779460907,
                            0.2125910073518753,
                            0.8741762638092041
                        ]
                    }
                }
            ],
            "script": "QuaternionBehaviorTrackScript",
            "accessor": "RotationQBlendAccessor"
        },
        {
            "@class": "Vector3BehaviorTrack",
            "clips": [
                {
                    "@class": "Vector3BehaviorClip",
                    "beginTime": 0,
                    "duration": 433,
                    "script": "Vector3ValueBehaviorClipScript",
                    "behavior": {
                        "@class": "Vector3PlainBehavior",
                        "times": [
                            0,
                            33,
                            66,
                            99,
                            133,
                            166,
                            199,
                            233,
                            266,
                            299,
                            333,
                            366,
                            399,
                            433
                        ],
                        "values": [
                            0.9999997615814209,
                            0.9999998211860657,
                            0.9999993443489075,
                            0.9999997615814209,
                            0.9999998211860657,
                            0.9999993443489075,
                            0.9999997615814209,
                            0.9999998211860657,
                            0.9999993443489075,
                            0.9999997615814209,
                            0.9999998211860657,
                            0.9999993443489075,
                            0.9999997615814209,
                            0.9999998211860657,
                            0.9999992847442627,
                            0.9999997615814209,
                            0.9999998211860657,
                            0.9999992847442627,
                            0.9999997615814209,
                            0.9999997615814209,
                            0.9999993443489075,
                            0.9999998211860657,
                            0.9999998211860657,
                            0.9999992847442627,
                            0.9999997019767761,
                            0.9999998211860657,
                            0.9999992847442627,
                            0.9999997615814209,
                            0.9999998211860657,
                            0.9999992847442627,
                            0.9999997615814209,
                            0.9999998211860657,
                            0.9999992847442627,
                            0.9999998211860657,
                            0.9999997615814209,
                            0.9999993443489075,
                            0.9999997615814209,
                            0.9999998211860657,
                            0.9999992847442627,
                            0.9999998211860657,
                            0.9999998211860657,
                            0.9999993443489075
                        ]
                    }
                }
            ],
            "script": "Vector3BehaviorTrackScript",
            "accessor": "ScaleBlendAccessor"
        }
    ]
}