{"@class":"Animation","id":{"uuid":"477509F0-24B5-4CC4-A8EF-37FDE0BAF5BC"},"tracks":[{"@class":"Vector3BehaviorTrack","clips":[{"@class":"Vector3BehaviorClip","beginTime":0,"duration":1333,"script":"Vector3ValueBehaviorClipScript","behavior":{"@class":"Vector3PlainBehavior","times":[0,1333],"values":[-0.000015169382095336914,0.039024773985147479,1.043081283569336e-7,-0.000015169382095336914,0.039024773985147479,1.043081283569336e-7]}}],"script":"Vector3BehaviorTrackScript","accessor":"PositionBlendAccessor"},{"@class":"QuaternionBehaviorTrack","clips":[{"@class":"QuaternionBehaviorClip","beginTime":0,"duration":1333,"script":"QuaternionValueBehaviorClipScript","behavior":{"@class":"QuaternionPlainBehavior","times":[0,1333],"values":[0.15138326585292817,-3.1657279464525347e-7,6.029959109810079e-8,0.9884751439094544,0.15138326585292817,-3.1657279464525347e-7,6.029959109810079e-8,0.9884751439094544]}}],"script":"QuaternionBehaviorTrackScript","accessor":"RotationQBlendAccessor"},{"@class":"Vector3BehaviorTrack","clips":[{"@class":"Vector3BehaviorClip","beginTime":0,"duration":1333,"script":"Vector3ValueBehaviorClipScript","behavior":{"@class":"Vector3PlainBehavior","times":[0,1333],"values":[1.0000001192092896,1.0,1.0000001192092896,1.0000001192092896,1.0,1.0000001192092896]}}],"script":"Vector3BehaviorTrackScript","accessor":"ScaleBlendAccessor"}]}