{"@class":"Animation","id":{"uuid":"56DCB0B3-5B8D-4EB7-B53F-58D9E7BC884C"},"tracks":[{"@class":"Vector3BehaviorTrack","clips":[{"@class":"Vector3BehaviorClip","beginTime":0,"duration":499,"script":"Vector3ValueBehaviorClipScript","behavior":{"@class":"Vector3PlainBehavior","times":[0,499],"values":[-0.000044288113713264468,0.036707259714603427,2.2351741790771486e-8,-0.00004430115222930908,0.03670715540647507,-4.842877388000488e-8]}}],"script":"Vector3BehaviorTrackScript","accessor":"PositionBlendAccessor"},{"@class":"QuaternionBehaviorTrack","clips":[{"@class":"QuaternionBehaviorClip","beginTime":0,"duration":499,"script":"QuaternionValueBehaviorClipScript","behavior":{"@class":"QuaternionPlainBehavior","times":[0,499],"values":[0.1928044557571411,-5.642583573717275e-7,4.828703836778914e-8,0.9812371730804443,0.1928044855594635,-5.673430223396281e-7,5.338863573456365e-8,0.9812371730804443]}}],"script":"QuaternionBehaviorTrackScript","accessor":"RotationQBlendAccessor"},{"@class":"Vector3BehaviorTrack","clips":[{"@class":"Vector3BehaviorClip","beginTime":0,"duration":499,"script":"Vector3ValueBehaviorClipScript","behavior":{"@class":"Vector3PlainBehavior","times":[0,499],"values":[1.0000001192092896,1.0000001192092896,1.0000001192092896,1.0,1.0000001192092896,1.0]}}],"script":"Vector3BehaviorTrackScript","accessor":"ScaleBlendAccessor"}]}