{"@class":"Animation","id":{"uuid":"60AB9304-444A-4818-AF21-35FD7A5F54C1"},"tracks":[{"@class":"Vector3BehaviorTrack","clips":[{"@class":"Vector3BehaviorClip","beginTime":0,"duration":1333,"script":"Vector3ValueBehaviorClipScript","behavior":{"@class":"Vector3PlainBehavior","times":[0,1333],"values":[-0.01474064588546753,0.10558512806892395,-0.005821924656629562,-0.01474064588546753,0.10558512806892395,-0.005821924656629562]}}],"script":"Vector3BehaviorTrackScript","accessor":"PositionBlendAccessor"},{"@class":"QuaternionBehaviorTrack","clips":[{"@class":"QuaternionBehaviorClip","beginTime":0,"duration":1333,"script":"QuaternionValueBehaviorClipScript","behavior":{"@class":"QuaternionPlainBehavior","times":[0,1333],"values":[0.24391083419322968,-0.003109955694526434,-0.012563311494886876,0.9697113037109375,0.24391083419322968,-0.003109955694526434,-0.012563311494886876,0.9697113037109375]}}],"script":"QuaternionBehaviorTrackScript","accessor":"RotationQBlendAccessor"},{"@class":"Vector3BehaviorTrack","clips":[{"@class":"Vector3BehaviorClip","beginTime":0,"duration":1333,"script":"Vector3ValueBehaviorClipScript","behavior":{"@class":"Vector3PlainBehavior","times":[0,1333],"values":[0.9999998807907105,0.9999999403953552,1.0,0.9999998807907105,0.9999999403953552,1.0]}}],"script":"Vector3BehaviorTrackScript","accessor":"ScaleBlendAccessor"}]}