{"@class":"Animation","id":{"uuid":"75BD66B4-D1C4-4E9A-AA9D-71DCC8FF34C8"},"tracks":[{"@class":"Vector3BehaviorTrack","clips":[{"@class":"Vector3BehaviorClip","beginTime":0,"duration":333,"script":"Vector3ValueBehaviorClipScript","behavior":{"@class":"Vector3PlainBehavior","times":[0,333],"values":[0.0029782280325889589,0.044356174767017367,1.1175870895385743e-8,0.0029782168567180635,0.0443560928106308,-1.4901161193847657e-8]}}],"script":"Vector3BehaviorTrackScript","accessor":"PositionBlendAccessor"},{"@class":"QuaternionBehaviorTrack","clips":[{"@class":"QuaternionBehaviorClip","beginTime":0,"duration":333,"script":"QuaternionValueBehaviorClipScript","behavior":{"@class":"QuaternionPlainBehavior","times":[0,333],"values":[5.6461431086063389e-9,9.96515154838562e-8,2.7008354663848878e-8,1.0,4.6566128730773929e-9,1.0803343286625022e-7,1.4901161193847657e-8,1.0]}}],"script":"QuaternionBehaviorTrackScript","accessor":"RotationQBlendAccessor"},{"@class":"Vector3BehaviorTrack","clips":[{"@class":"Vector3BehaviorClip","beginTime":0,"duration":333,"script":"Vector3ValueBehaviorClipScript","behavior":{"@class":"Vector3PlainBehavior","times":[0,333],"values":[0.9999999403953552,1.0,1.0000001192092896,1.0,0.9999998211860657,0.9999999403953552]}}],"script":"Vector3BehaviorTrackScript","accessor":"ScaleBlendAccessor"}]}