{"@class":"Animation","id":{"uuid":"8DFE01FD-D1B8-4DFF-8622-BC3B120319B1"},"tracks":[{"@class":"TimeLineTrack","clips":[{"@class":"TimeLineClip","beginTime":2500,"duration":27500,"script":"TimeLineClipScript","behavior":{"@class":"TimeLineBehavior","speed":1.0,"weights":{}},"bindinglink":{"@class":"BindingLink","targetId":{"uuid":"9860CF8B-0E80-47EF-BF05-0A1CDEE64F0B"}},"color":{"values":[0.0,0.0,0.0]}}],"script":"TimeLineTrackScript","accessor":"TimeLineAccessor"},{"@class":"TimeLineTrack","clips":[{"@class":"TimeLineClip","beginTime":2500,"duration":27500,"script":"TimeLineClipScript","behavior":{"@class":"TimeLineBehavior","speed":1.0,"weights":{}},"bindinglink":{"@class":"BindingLink","targetId":{"uuid":"4E1E412D-9818-401F-8299-9521FBCE7BA5"}},"color":{"values":[0.0,0.0,0.0]}}],"script":"TimeLineTrackScript","accessor":"TimeLineAccessor"},{"@class":"TimeLineTrack","clips":[{"@class":"TimeLineClip","beginTime":1350,"duration":700,"script":"TimeLineClipScript","behavior":{"@class":"TimeLineBehavior","speed":1.0,"weights":{}},"bindinglink":{"@class":"BindingLink","targetId":{"uuid":"3D8E9898-0C31-412B-9825-2E46175CED12"}},"color":{"values":[0.0,0.0,0.0]}}],"script":"TimeLineTrackScript","accessor":"TimeLineAccessor"},{"@class":"TimeLineTrack","clips":[{"@class":"TimeLineClip","beginTime":700,"duration":1000,"script":"TimeLineClipScript","behavior":{"@class":"TimeLineBehavior","speed":1.0,"weights":{}},"bindinglink":{"@class":"BindingLink","targetId":{"uuid":"0547CB8D-939D-453D-894A-BFF02828CF92"}},"color":{"values":[0.0,0.0,0.0]}}],"script":"TimeLineTrackScript","accessor":"TimeLineAccessor"}]}