{"@class":"Animation","id":{"uuid":"A20ECC55-AAFF-4BA3-A1C0-9E82D11EB341"},"tracks":[{"@class":"Vector3BehaviorTrack","clips":[{"@class":"Vector3BehaviorClip","beginTime":0,"duration":833,"script":"Vector3ValueBehaviorClipScript","behavior":{"@class":"Vector3PlainBehavior","times":[0,833],"values":[0.00004420056939125061,0.03670724481344223,-8.754432201385498e-8,0.00004420056939125061,0.03670724481344223,-8.754432201385498e-8]}}],"script":"Vector3BehaviorTrackScript","accessor":"PositionBlendAccessor"},{"@class":"QuaternionBehaviorTrack","clips":[{"@class":"QuaternionBehaviorClip","beginTime":0,"duration":833,"script":"QuaternionValueBehaviorClipScript","behavior":{"@class":"QuaternionPlainBehavior","times":[0,833],"values":[0.19280444085597993,5.770716029473988e-7,-5.125307467324092e-8,0.9812372326850891,0.19280444085597993,5.770716029473988e-7,-5.125307467324092e-8,0.9812372326850891]}}],"script":"QuaternionBehaviorTrackScript","accessor":"RotationQBlendAccessor"},{"@class":"Vector3BehaviorTrack","clips":[{"@class":"Vector3BehaviorClip","beginTime":0,"duration":833,"script":"Vector3ValueBehaviorClipScript","behavior":{"@class":"Vector3PlainBehavior","times":[0,833],"values":[0.9999999403953552,1.0,0.9999999403953552,0.9999999403953552,1.0,0.9999999403953552]}}],"script":"Vector3BehaviorTrackScript","accessor":"ScaleBlendAccessor"}]}