{"@class":"TimeLineScript","id":{"uuid":"0DC6E6A0-9B6C-440C-82D9-2CA49B8FB6F3"},"name":"Animation","enableOnAwake":false,"loop":false,"jumpToFirstFrameAtEnd":false,"speed":1.0,"weight":1.0,"loopStartTime":0,"loopDuration":0,"is_imported":false,"type":"user","scripts":{"@class":"StdListRuntimeScript","list":[{"@class":"AnimationScript","id":{"uuid":"B5894A62-8251-4C4A-AD6D-272BA8088D51"},"name":"Crystal_01","enableOnAwake":false,"OwnerLink":{"@class":"BindingLink","targetId":{"uuid":"22209AAA-437B-4424-96C5-F8C34FB43403"},"targetRelativeAddress":{"@class":"NodeRelativeAddressBase","index":9,"name":"Crystal_02 23"}},"animation":{"uuid":"36B08A38-E7CB-441B-BBCF-1BCB2AAB9E02"},"AnimationType":"object3D","is_imported":false,"isEnabled":true},{"@class":"AnimationScript","id":{"uuid":"91CD8F7C-A86A-464C-B80C-C1140FDECB79"},"name":"Master Sound","enableOnAwake":false,"OwnerLink":{"@class":"BindingLink"},"animation":{"uuid":"FE415C4D-2763-4AB1-9F0E-3B595F89219B"},"AnimationType":"masterSound","is_imported":false,"isEnabled":true}]},"triggers":[{"@class":"CollisionTrigger","id":{"uuid":"BCFA0ECB-A6F9-4631-9B50-77D09B273BE9"},"ownerScriptId":{"uuid":"0DC6E6A0-9B6C-440C-82D9-2CA49B8FB6F3"},"logicOperation":0,"resultType":0,"isInverted":false,"eventType":"in","targetBindingLink":{"@class":"BindingLink","targetId":{"uuid":"C95EA845-BC44-4DCC-857D-B0257C48D480"}},"zoneBindingLink":{"@class":"BindingLink","targetId":{"uuid":"22209AAA-437B-4424-96C5-F8C34FB43403"},"targetRelativeAddress":{"@class":"NodeRelativeAddressBase","index":9,"name":"Crystal_02 23"}},"allowed":false}]}