{"@class":"TimeLineScript","id":{"uuid":"1B1A4A82-C1D7-4FDB-9B21-4E048D1AE404"},"name":"Animation","enableOnAwake":false,"loop":false,"jumpToFirstFrameAtEnd":false,"speed":1.0,"weight":1.0,"loopStartTime":0,"loopDuration":0,"is_imported":false,"type":"user","scripts":{"@class":"StdListRuntimeScript","list":[{"@class":"AnimationScript","id":{"uuid":"ACA13239-E45D-43E5-9F69-3BF6F4C10539"},"name":"Inserted animations","enableOnAwake":false,"OwnerLink":{"@class":"BindingLink"},"animation":{"uuid":"99B9FC6D-903A-4B94-8DE0-1C74B1DB2DCD"},"AnimationType":"timeline","is_imported":false,"isEnabled":true}]},"triggers":[{"@class":"CollisionTrigger","id":{"uuid":"305E1F8E-3BD8-40EA-A77F-1BFA80867610"},"ownerScriptId":{"uuid":"1B1A4A82-C1D7-4FDB-9B21-4E048D1AE404"},"logicOperation":0,"resultType":0,"isInverted":false,"eventType":"in","targetBindingLink":{"@class":"BindingLink","targetId":{"uuid":"C95EA845-BC44-4DCC-857D-B0257C48D480"}},"zoneBindingLink":{"@class":"BindingLink","targetId":{"uuid":"96A7D9AB-3283-4A38-9F00-CABBBB11909D"},"targetRelativeAddress":{"@class":"NodeRelativeAddressBase","index":2,"name":"Trap_Gear_2_5m"}},"allowed":false}]}