{"@class":"TimeLineScript","id":{"uuid":"80410F77-4B96-4FFC-8765-0AEB1FD96096"},"name":"Animation","enableOnAwake":false,"loop":true,"jumpToFirstFrameAtEnd":false,"speed":1.0,"weight":1.0,"loopStartTime":0,"loopDuration":0,"is_imported":false,"type":"user","scripts":{"@class":"StdListRuntimeScript","list":[{"@class":"AnimationScript","id":{"uuid":"7A4B5F89-0612-4A6F-BE7C-819A88AF0FAA"},"name":"Crystal_01","enableOnAwake":false,"OwnerLink":{"@class":"BindingLink","targetId":{"uuid":"D295D59B-581C-4747-8BCA-848B28C45C68"},"targetRelativeAddress":{"@class":"NodeRelativeAddressBase","index":15,"name":"Crystal_02 5"}},"animation":{"uuid":"FCC666F2-14C1-4D06-950F-9086573DEDBE"},"AnimationType":"object3D","is_imported":false,"isEnabled":true}]},"triggers":[{"@class":"StartTrigger","id":{"uuid":"E26DAF10-4ADA-4A56-B19B-FA252F76F473"},"ownerScriptId":{"uuid":"80410F77-4B96-4FFC-8765-0AEB1FD96096"},"logicOperation":0,"resultType":0,"isInverted":false}]}