{"@class":"TimeLineScript","id":{"uuid":"A9EA2E49-2D0D-4BA4-B903-DB7C2AD4A198"},"name":"Animation","enableOnAwake":false,"loop":false,"jumpToFirstFrameAtEnd":false,"speed":1.0,"weight":1.0,"loopStartTime":0,"loopDuration":0,"is_imported":false,"type":"user","scripts":{"@class":"StdListRuntimeScript","list":[{"@class":"AnimationScript","id":{"uuid":"1D11DC96-C4CE-4AAA-B2F8-2FBABCFC8307"},"name":"Crystal_01","enableOnAwake":false,"OwnerLink":{"@class":"BindingLink","targetId":{"uuid":"5AEAFBA5-F996-445B-A46B-F6BAAFAF111C"},"targetRelativeAddress":{"@class":"NodeRelativeAddressBase","index":32,"name":"Crystal 19"}},"animation":{"uuid":"EDBD88E8-AD38-4CC2-AF7A-17FE17545230"},"AnimationType":"object3D","is_imported":false,"isEnabled":true},{"@class":"AnimationScript","id":{"uuid":"632F0B3B-5F26-4F2E-8EED-0903F47D46C0"},"name":"Crystal","enableOnAwake":false,"OwnerLink":{"@class":"BindingLink","targetId":{"uuid":"C43013D7-7DC1-467D-9F77-C12A01A17874"},"targetRelativeAddress":{"@class":"NodeRelativeAddressBase","index":32,"name":"Crystal 19","subaddress":{"@class":"NodeRelativeAddressBase","index":0,"name":"Crystal"}}},"animation":{"uuid":"2180D20D-96A8-40A4-AC06-778ED91F9DDB"},"AnimationType":"object3D","is_imported":false,"isEnabled":true},{"@class":"AnimationScript","id":{"uuid":"301CAD1E-961D-464D-982B-A0770B17F239"},"name":"Master Sound","enableOnAwake":false,"OwnerLink":{"@class":"BindingLink"},"animation":{"uuid":"7071269D-E3D2-4B0C-A089-B540813E3D76"},"AnimationType":"masterSound","is_imported":false,"isEnabled":true}]},"triggers":[{"@class":"CollisionTrigger","id":{"uuid":"9A10CC06-0DBF-4D46-845E-18A81997268F"},"ownerScriptId":{"uuid":"A9EA2E49-2D0D-4BA4-B903-DB7C2AD4A198"},"logicOperation":0,"resultType":0,"isInverted":false,"eventType":"in","targetBindingLink":{"@class":"BindingLink","targetId":{"uuid":"C95EA845-BC44-4DCC-857D-B0257C48D480"}},"zoneBindingLink":{"@class":"BindingLink","targetId":{"uuid":"C43013D7-7DC1-467D-9F77-C12A01A17874"},"targetRelativeAddress":{"@class":"NodeRelativeAddressBase","index":32,"name":"Crystal 19","subaddress":{"@class":"NodeRelativeAddressBase","index":0,"name":"Crystal"}}},"allowed":false}]}