{"@class":"TimeLineScript","id":{"uuid":"C3870662-368E-4B36-A1CD-750F745D8DD2"},"name":"Animation","enableOnAwake":false,"loop":false,"jumpToFirstFrameAtEnd":false,"speed":1.0,"weight":1.0,"loopStartTime":0,"loopDuration":0,"is_imported":false,"type":"user","scripts":{"@class":"StdListRuntimeScript","list":[{"@class":"AnimationScript","id":{"uuid":"D593FE0A-82D5-4532-9B94-BFF2D463B40D"},"name":"Crystal_01","enableOnAwake":false,"OwnerLink":{"@class":"BindingLink","targetId":{"uuid":"4676E424-50BE-43EE-9D76-26408E27DD1D"},"targetRelativeAddress":{"@class":"NodeRelativeAddressBase","index":12,"name":"Crystal_02 25"}},"animation":{"uuid":"D092CAD8-5F22-4DDA-925B-80BA14D10C56"},"AnimationType":"object3D","is_imported":false,"isEnabled":true},{"@class":"AnimationScript","id":{"uuid":"8E43E6E8-27CC-4BFB-8C65-5EA8319C73F2"},"name":"Master Sound","enableOnAwake":false,"OwnerLink":{"@class":"BindingLink"},"animation":{"uuid":"4D968C83-F4CF-43BE-ACFD-6776CFC39505"},"AnimationType":"masterSound","is_imported":false,"isEnabled":true}]},"triggers":[{"@class":"CollisionTrigger","id":{"uuid":"FEE1F9E7-5EF9-4793-8B0D-BA6BC6658D36"},"ownerScriptId":{"uuid":"C3870662-368E-4B36-A1CD-750F745D8DD2"},"logicOperation":0,"resultType":0,"isInverted":false,"eventType":"in","targetBindingLink":{"@class":"BindingLink","targetId":{"uuid":"C95EA845-BC44-4DCC-857D-B0257C48D480"}},"zoneBindingLink":{"@class":"BindingLink","targetId":{"uuid":"4676E424-50BE-43EE-9D76-26408E27DD1D"},"targetRelativeAddress":{"@class":"NodeRelativeAddressBase","index":12,"name":"Crystal_02 25"}},"allowed":true}]}