{
    "@class": "Animation",
    "id": {
        "uuid": "D3115225-892D-4281-8960-3A10B656E0B0"
    },
    "tracks": [
        {
            "@class": "BoolBehaviorTrack",
            "clips": [
                {
                    "@class": "BoolBehaviorClip",
                    "beginTime": 0,
                    "duration": 500,
                    "script": "BoolValueBehaviorClipScript",
                    "behavior": {
                        "@class": "BoolDiscreteBehavior",
                        "frames": [
                            {
                                "@class": "BoolKeyFrame",
                                "formula": {
                                    "@class": "BoolExpressionFormula",
                                    "expression": "false"
                                },
                                "time": 500
                            }
                        ]
                    }
                }
            ],
            "script": "BoolBehaviorTrackScript",
            "accessor": "Object3DEnabledBlendAccessor"
        }
    ]
}